{
  "set": {
    "id": 790815397,
    "timestamp": 1680816988,
    "lastModified": 1680817013,
    "publishedTimestamp": 1680817013,
    "wordLang": "en",
    "defLang": "en",
    "title": "Disney Princess Trivia",
    "description": "",
    "numTerms": 22,
    "hasImages": true,
    "hasDiagrams": false,
    "_webUrl": "https://quizlet.com/790815397/disney-princess-trivia-flash-cards/"
  },
  "studiableItem": [
    {
      "id": 1762464355127296,
      "studiableContainerType": 1,
      "studiableContainerId": 790815397,
      "type": 2,
      "rank": 0,
      "creatorId": 305811011,
      "timestamp": 1555426069,
      "lastModified": 1680816988,
      "isDeleted": false,
      "cardSides": [
        {
          "sideId": 1,
          "label": "word",
          "media": [
            {
              "type": 1,
              "plainText": "Woody",
              "languageCode": "en",
              "richText": null
            }
          ]
        },
        {
          "sideId": 2,
          "label": "definition",
          "media": [
            {
              "type": 1,
              "plainText": "He was worried about being replaced by a new toy.",
              "languageCode": "en",
              "richText": null
            },
            {
              "type": 2,
              "code": "86PaCPzgDn4X6M89",
              "url": "https://o.quizlet.com/THalR.XHHWZjqUUfg9mzKw_m.png",
              "width": 961,
              "height": 697
            }
          ]
        }
      ]
    },
    {
      "id": 1762464355127297,
      "studiableContainerType": 1,
      "studiableContainerId": 790815397,
      "type": 2,
      "rank": 1,
      "creatorId": 305811011,
      "timestamp": 1555426069,
      "lastModified": 1680816988,
      "isDeleted": false,
      "cardSides": [
        {
          "sideId": 1,
          "label": "word",
          "media": [
            {
              "type": 1,
              "plainText": "Beauty and the Beast",
              "languageCode": "en",
              "richText": null
            }
          ]
        },
        {
          "sideId": 2,
          "label": "definition",
          "media": [
            {
              "type": 1,
              "plainText": "The movie where a young girl falls in love with a creature.",
              "languageCode": "en",
              "richText": null
            },
            {
              "type": 2,
              "code": "8Mqv538WZsjvWFUX",
              "url": "https://o.quizlet.com/lCHVw3TJuITUyFmss-31fQ_m.jpg",
              "width": 259,
              "height": 194
            }
          ]
        }
      ]
    },
    {
      "id": 1762464355127298,
      "studiableContainerType": 1,
      "studiableContainerId": 790815397,
      "type": 2,
      "rank": 2,
      "creatorId": 305811011,
      "timestamp": 1555426069,
      "lastModified": 1680816988,
      "isDeleted": false,
      "cardSides": [
        {
          "sideId": 1,
          "label": "word",
          "media": [
            {
              "type": 1,
              "plainText": "Tinker Bell",
              "languageCode": "en",
              "richText": null
            }
          ]
        },
        {
          "sideId": 2,
          "label": "definition",
          "media": [
            {
              "type": 1,
              "plainText": "She is Peter's friend.",
              "languageCode": "en",
              "richText": null
            },
            {
              "type": 2,
              "code": "4CTgXBate3z6fcSr",
              "url": "https://o.quizlet.com/oQbRAC2HQX9Jk58GjBhDCA_m.gif",
              "width": 500,
              "height": 375
            }
          ]
        }
      ]
    },
    {
      "id": 1762464355127299,
      "studiableContainerType": 1,
      "studiableContainerId": 790815397,
      "type": 2,
      "rank": 3,
      "creatorId": 305811011,
      "timestamp": 1555426069,
      "lastModified": 1680816988,
      "isDeleted": false,
      "cardSides": [
        {
          "sideId": 1,
          "label": "word",
          "media": [
            {
              "type": 1,
              "plainText": "Mushu",
              "languageCode": "en",
              "richText": null
            }
          ]
        },
        {
          "sideId": 2,
          "label": "definition",
          "media": [
            {
              "type": 1,
              "plainText": "His job is to restore honor to the family.",
              "languageCode": "en",
              "richText": null
            },
            {
              "type": 2,
              "code": "zBJXcsBCabXxCDfC",
              "url": "https://o.quizlet.com/zLovsmvmtl64S5lkDtu2Nw_m.jpg",
              "width": 1024,
              "height": 768
            }
          ]
        }
      ]
    },
    {
      "id": 1762464355127300,
      "studiableContainerType": 1,
      "studiableContainerId": 790815397,
      "type": 2,
      "rank": 4,
      "creatorId": 305811011,
      "timestamp": 1555426069,
      "lastModified": 1680816988,
      "isDeleted": false,
      "cardSides": [
        {
          "sideId": 1,
          "label": "word",
          "media": [
            {
              "type": 1,
              "plainText": "Snow White",
              "languageCode": "en",
              "richText": null
            }
          ]
        },
        {
          "sideId": 2,
          "label": "definition",
          "media": [
            {
              "type": 1,
              "plainText": "She lives with seven men, but loves only one prince.",
              "languageCode": "en",
              "richText": null
            },
            {
              "type": 2,
              "code": "snzhssAFzXXR6nAy",
              "url": "https://o.quizlet.com/4rOzhNC9HxgQmSA7JO5VyQ_m.gif",
              "width": 500,
              "height": 374
            }
          ]
        }
      ]
    },
    {
      "id": 1762464355127301,
      "studiableContainerType": 1,
      "studiableContainerId": 790815397,
      "type": 2,
      "rank": 5,
      "creatorId": 305811011,
      "timestamp": 1555426069,
      "lastModified": 1680816988,
      "isDeleted": false,
      "cardSides": [
        {
          "sideId": 1,
          "label": "word",
          "media": [
            {
              "type": 1,
              "plainText": "Walt Disney",
              "languageCode": "en",
              "richText": null
            }
          ]
        },
        {
          "sideId": 2,
          "label": "definition",
          "media": [
            {
              "type": 1,
              "plainText": "The creator of the Magical Kingdom.",
              "languageCode": "en",
              "richText": null
            },
            {
              "type": 2,
              "code": "n8ygyGRVpCN5f9Wx",
              "url": "https://o.quizlet.com/-CYem59DxcY-gKlWRF98uQ_m.gif",
              "width": 500,
              "height": 280
            }
          ]
        }
      ]
    },
    {
      "id": 1762464355127303,
      "studiableContainerType": 1,
      "studiableContainerId": 790815397,
      "type": 2,
      "rank": 6,
      "creatorId": 305811011,
      "timestamp": 1555426069,
      "lastModified": 1680816988,
      "isDeleted": false,
      "cardSides": [
        {
          "sideId": 1,
          "label": "word",
          "media": [
            {
              "type": 1,
              "plainText": "Rapunzel",
              "languageCode": "en",
              "richText": null
            }
          ]
        },
        {
          "sideId": 2,
          "label": "definition",
          "media": [
            {
              "type": 1,
              "plainText": "She can't keep her hair to herself.",
              "languageCode": "en",
              "richText": null
            },
            {
              "type": 2,
              "code": "af2g34m5sD6Y2d7m",
              "url": "https://o.quizlet.com/MbKRhhbKfRQySGdquFolug_m.jpg",
              "width": 295,
              "height": 171
            }
          ]
        }
      ]
    },
    {
      "id": 1762464355127304,
      "studiableContainerType": 1,
      "studiableContainerId": 790815397,
      "type": 2,
      "rank": 7,
      "creatorId": 305811011,
      "timestamp": 1555426069,
      "lastModified": 1680816988,
      "isDeleted": false,
      "cardSides": [
        {
          "sideId": 1,
          "label": "word",
          "media": [
            {
              "type": 1,
              "plainText": "Ariel",
              "languageCode": "en",
              "richText": null
            }
          ]
        },
        {
          "sideId": 2,
          "label": "definition",
          "media": [
            {
              "type": 1,
              "plainText": "She wants to be where the people are.",
              "languageCode": "en",
              "richText": null
            },
            {
              "type": 2,
              "code": "BCQM7u4vexGAQYS2",
              "url": "https://o.quizlet.com/rM-oEO13ZwuBDahT-hNQ6Q_m.jpg",
              "width": 1528,
              "height": 1788
            }
          ]
        }
      ]
    },
    {
      "id": 1762464355127305,
      "studiableContainerType": 1,
      "studiableContainerId": 790815397,
      "type": 2,
      "rank": 8,
      "creatorId": 305811011,
      "timestamp": 1555426069,
      "lastModified": 1680816988,
      "isDeleted": false,
      "cardSides": [
        {
          "sideId": 1,
          "label": "word",
          "media": [
            {
              "type": 1,
              "plainText": "Cinderella",
              "languageCode": "en",
              "richText": null
            }
          ]
        },
        {
          "sideId": 2,
          "label": "definition",
          "media": [
            {
              "type": 1,
              "plainText": "She just can't keep her shoe on.",
              "languageCode": "en",
              "richText": null
            },
            {
              "type": 2,
              "code": "tQzSAhgpWaBvEdSD",
              "url": "https://o.quizlet.com/i/V7joBhQJMrcxhvv-QCWD2Q_m.jpg",
              "width": 181,
              "height": 285
            }
          ]
        }
      ]
    },
    {
      "id": 1762464355127306,
      "studiableContainerType": 1,
      "studiableContainerId": 790815397,
      "type": 2,
      "rank": 9,
      "creatorId": 305811011,
      "timestamp": 1555426069,
      "lastModified": 1680816988,
      "isDeleted": false,
      "cardSides": [
        {
          "sideId": 1,
          "label": "word",
          "media": [
            {
              "type": 1,
              "plainText": "Mr. Incredible",
              "languageCode": "en",
              "richText": null
            }
          ]
        },
        {
          "sideId": 2,
          "label": "definition",
          "media": [
            {
              "type": 1,
              "plainText": "He just wants to be super!",
              "languageCode": "en",
              "richText": null
            },
            {
              "type": 2,
              "code": "hNqrYdnK4K65cMuB",
              "url": "https://o.quizlet.com/iXpWLW0ouVuKwSY0Y2j12w_m.jpg",
              "width": 192,
              "height": 263
            }
          ]
        }
      ]
    },
    {
      "id": 1762464355127307,
      "studiableContainerType": 1,
      "studiableContainerId": 790815397,
      "type": 2,
      "rank": 10,
      "creatorId": 305811011,
      "timestamp": 1555426069,
      "lastModified": 1680816988,
      "isDeleted": false,
      "cardSides": [
        {
          "sideId": 1,
          "label": "word",
          "media": [
            {
              "type": 1,
              "plainText": "Alice",
              "languageCode": "en",
              "richText": null
            }
          ]
        },
        {
          "sideId": 2,
          "label": "definition",
          "media": [
            {
              "type": 1,
              "plainText": "She falls down the rabbit hole.",
              "languageCode": "en",
              "richText": null
            },
            {
              "type": 2,
              "code": "7B73CQUj6ZqTjw6G",
              "url": "https://o.quizlet.com/qzG50DYnndA8exfJwEoHvA_m.jpg",
              "width": 420,
              "height": 432
            }
          ]
        }
      ]
    },
    {
      "id": 1762464355127308,
      "studiableContainerType": 1,
      "studiableContainerId": 790815397,
      "type": 2,
      "rank": 11,
      "creatorId": 305811011,
      "timestamp": 1555426069,
      "lastModified": 1680816988,
      "isDeleted": false,
      "cardSides": [
        {
          "sideId": 1,
          "label": "word",
          "media": [
            {
              "type": 1,
              "plainText": "Belle",
              "languageCode": "en",
              "richText": null
            }
          ]
        },
        {
          "sideId": 2,
          "label": "definition",
          "media": [
            {
              "type": 1,
              "plainText": "She breaks the spell on an enchanted castle.",
              "languageCode": "en",
              "richText": null
            },
            {
              "type": 2,
              "code": "8Mqv538WZsjvWFUX",
              "url": "https://o.quizlet.com/lCHVw3TJuITUyFmss-31fQ_m.jpg",
              "width": 259,
              "height": 194
            }
          ]
        }
      ]
    },
    {
      "id": 1762464355127309,
      "studiableContainerType": 1,
      "studiableContainerId": 790815397,
      "type": 2,
      "rank": 12,
      "creatorId": 305811011,
      "timestamp": 1555426069,
      "lastModified": 1680816988,
      "isDeleted": false,
      "cardSides": [
        {
          "sideId": 1,
          "label": "word",
          "media": [
            {
              "type": 1,
              "plainText": "Nemo",
              "languageCode": "en",
              "richText": null
            }
          ]
        },
        {
          "sideId": 2,
          "label": "definition",
          "media": [
            {
              "type": 1,
              "plainText": "He finds himself needing to be rescued.",
              "languageCode": "en",
              "richText": null
            },
            {
              "type": 2,
              "code": "tbGTUCTSQGeA4RyZ",
              "url": "https://o.quizlet.com/i/XftcnO6GyXTvEIx3oXlS_g_m.jpg",
              "width": 472,
              "height": 359
            }
          ]
        }
      ]
    },
    {
      "id": 1762464355127310,
      "studiableContainerType": 1,
      "studiableContainerId": 790815397,
      "type": 2,
      "rank": 13,
      "creatorId": 305811011,
      "timestamp": 1555426069,
      "lastModified": 1680816988,
      "isDeleted": false,
      "cardSides": [
        {
          "sideId": 1,
          "label": "word",
          "media": [
            {
              "type": 1,
              "plainText": "Bambi",
              "languageCode": "en",
              "richText": null
            }
          ]
        },
        {
          "sideId": 2,
          "label": "definition",
          "media": [
            {
              "type": 1,
              "plainText": "Thumper's friend.",
              "languageCode": "en",
              "richText": null
            },
            {
              "type": 2,
              "code": "z9eECgd5r6BkkFDy",
              "url": "https://o.quizlet.com/eGXasCU9.UFEYF9Ido6vEA_m.jpg",
              "width": 284,
              "height": 178
            }
          ]
        }
      ]
    },
    {
      "id": 1762464355127311,
      "studiableContainerType": 1,
      "studiableContainerId": 790815397,
      "type": 2,
      "rank": 14,
      "creatorId": 305811011,
      "timestamp": 1555426069,
      "lastModified": 1680816988,
      "isDeleted": false,
      "cardSides": [
        {
          "sideId": 1,
          "label": "word",
          "media": [
            {
              "type": 1,
              "plainText": "Simba",
              "languageCode": "en",
              "richText": null
            }
          ]
        },
        {
          "sideId": 2,
          "label": "definition",
          "media": [
            {
              "type": 1,
              "plainText": "He just can't wait to be king.",
              "languageCode": "en",
              "richText": null
            },
            {
              "type": 2,
              "code": "3jK6m9xseVvcAnt9",
              "url": "https://o.quizlet.com/i/6fjSo1Y43vUHZ-777lr5rA_m.jpg",
              "width": 240,
              "height": 171
            }
          ]
        }
      ]
    },
    {
      "id": 1762464355127312,
      "studiableContainerType": 1,
      "studiableContainerId": 790815397,
      "type": 2,
      "rank": 15,
      "creatorId": 305811011,
      "timestamp": 1555426069,
      "lastModified": 1680816988,
      "isDeleted": false,
      "cardSides": [
        {
          "sideId": 1,
          "label": "word",
          "media": [
            {
              "type": 1,
              "plainText": "Captain Hook",
              "languageCode": "en",
              "richText": null
            }
          ]
        },
        {
          "sideId": 2,
          "label": "definition",
          "media": [
            {
              "type": 1,
              "plainText": "Peter Pan's enemy.",
              "languageCode": "en",
              "richText": null
            },
            {
              "type": 2,
              "code": "z9CbMskKHrMXAzPG",
              "url": "https://o.quizlet.com/cWdW7SzvqBorToEeVRKEtA_m.jpg",
              "width": 1000,
              "height": 1000
            }
          ]
        }
      ]
    },
    {
      "id": 1762464355127313,
      "studiableContainerType": 1,
      "studiableContainerId": 790815397,
      "type": 2,
      "rank": 16,
      "creatorId": 305811011,
      "timestamp": 1555426069,
      "lastModified": 1680816988,
      "isDeleted": false,
      "cardSides": [
        {
          "sideId": 1,
          "label": "word",
          "media": [
            {
              "type": 1,
              "plainText": "Dumbo",
              "languageCode": "en",
              "richText": null
            }
          ]
        },
        {
          "sideId": 2,
          "label": "definition",
          "media": [
            {
              "type": 1,
              "plainText": "The flying elephant",
              "languageCode": "en",
              "richText": null
            },
            {
              "type": 2,
              "code": "w5rU5KazCNbG5UJN",
              "url": "https://o.quizlet.com/BCmKTX08sYeyPkR3JeGp-w_m.gif",
              "width": 150,
              "height": 113
            }
          ]
        }
      ]
    },
    {
      "id": 1762464355127314,
      "studiableContainerType": 1,
      "studiableContainerId": 790815397,
      "type": 2,
      "rank": 17,
      "creatorId": 305811011,
      "timestamp": 1555426069,
      "lastModified": 1680816988,
      "isDeleted": false,
      "cardSides": [
        {
          "sideId": 1,
          "label": "word",
          "media": [
            {
              "type": 1,
              "plainText": "Peter Pan",
              "languageCode": "en",
              "richText": null
            }
          ]
        },
        {
          "sideId": 2,
          "label": "definition",
          "media": [
            {
              "type": 1,
              "plainText": "He never wants to grow up.",
              "languageCode": "en",
              "richText": null
            },
            {
              "type": 2,
              "code": "wHXd9UfcE9rrxTx3",
              "url": "https://o.quizlet.com/i/vdwYvI4WSO3W0a91zRRxYA_m.jpg",
              "width": 400,
              "height": 300
            }
          ]
        }
      ]
    },
    {
      "id": 1762464355127315,
      "studiableContainerType": 1,
      "studiableContainerId": 790815397,
      "type": 2,
      "rank": 18,
      "creatorId": 305811011,
      "timestamp": 1555426069,
      "lastModified": 1680816988,
      "isDeleted": false,
      "cardSides": [
        {
          "sideId": 1,
          "label": "word",
          "media": [
            {
              "type": 1,
              "plainText": "Pinocchio",
              "languageCode": "en",
              "richText": null
            }
          ]
        },
        {
          "sideId": 2,
          "label": "definition",
          "media": [
            {
              "type": 1,
              "plainText": "The boy with a growing nose.",
              "languageCode": "en",
              "richText": null
            },
            {
              "type": 2,
              "code": "bpMnAF9qr2HXvxdF",
              "url": "https://o.quizlet.com/8J.XG2AswTIoPvEM8KgWlQ_m.jpg",
              "width": 227,
              "height": 222
            }
          ]
        }
      ]
    },
    {
      "id": 1762464355127316,
      "studiableContainerType": 1,
      "studiableContainerId": 790815397,
      "type": 2,
      "rank": 19,
      "creatorId": 305811011,
      "timestamp": 1555426069,
      "lastModified": 1680816988,
      "isDeleted": false,
      "cardSides": [
        {
          "sideId": 1,
          "label": "word",
          "media": [
            {
              "type": 1,
              "plainText": "Mike Wazowski",
              "languageCode": "en",
              "richText": null
            }
          ]
        },
        {
          "sideId": 2,
          "label": "definition",
          "media": [
            {
              "type": 1,
              "plainText": "He was Sully's University roommate.",
              "languageCode": "en",
              "richText": null
            },
            {
              "type": 2,
              "code": "RgnbZjNFZXZjHE9p",
              "url": "https://o.quizlet.com/z5CdLzyCC8a6C678TFV7OQ_m.png",
              "width": 209,
              "height": 117
            }
          ]
        }
      ]
    },
    {
      "id": 1762464355127317,
      "studiableContainerType": 1,
      "studiableContainerId": 790815397,
      "type": 2,
      "rank": 20,
      "creatorId": 305811011,
      "timestamp": 1555426069,
      "lastModified": 1680816988,
      "isDeleted": false,
      "cardSides": [
        {
          "sideId": 1,
          "label": "word",
          "media": [
            {
              "type": 1,
              "plainText": "101 Dalmations",
              "languageCode": "en",
              "richText": null
            }
          ]
        },
        {
          "sideId": 2,
          "label": "definition",
          "media": [
            {
              "type": 1,
              "plainText": "This dog was highlighted in this Disney movie.",
              "languageCode": "en",
              "richText": null
            },
            {
              "type": 2,
              "code": "p8PrfXzAkBHVJDX7",
              "url": "https://o.quizlet.com/ckaKIrFAC1T6q.5XeTcIog_m.jpg",
              "width": 271,
              "height": 186
            }
          ]
        }
      ]
    },
    {
      "id": 1762464355127318,
      "studiableContainerType": 1,
      "studiableContainerId": 790815397,
      "type": 2,
      "rank": 21,
      "creatorId": 305811011,
      "timestamp": 1555426069,
      "lastModified": 1680816988,
      "isDeleted": false,
      "cardSides": [
        {
          "sideId": 1,
          "label": "word",
          "media": [
            {
              "type": 1,
              "plainText": "Mowgli",
              "languageCode": "en",
              "richText": null
            }
          ]
        },
        {
          "sideId": 2,
          "label": "definition",
          "media": [
            {
              "type": 1,
              "plainText": "He was raised in the jungle.",
              "languageCode": "en",
              "richText": null
            },
            {
              "type": 2,
              "code": "ra77Rru4TBsknNbQ",
              "url": "https://o.quizlet.com/30SfqturxtKPVuBwDPFPlA_m.jpg",
              "width": 275,
              "height": 183
            }
          ]
        }
      ]
    }
  ]
}
